{
  "$schema": "https://schema.management.azure.com/schemas/2019-04-01/deploymentTemplate.json#",
  "contentVersion": "1.0.0.0",
  "metadata": {
    "_generator": {
      "name": "bicep",
      "version": "0.44.1.10279",
      "templateHash": "17986931304549633146"
    }
  },
  "parameters": {
    "location": {
      "type": "string",
      "defaultValue": "japaneast"
    },
    "registryName": {
      "type": "string",
      "defaultValue": "mlr-churn-shared-jpe"
    }
  },
  "resources": [
    {
      "type": "Microsoft.MachineLearningServices/registries",
      "apiVersion": "2024-04-01",
      "name": "[parameters('registryName')]",
      "location": "[parameters('location')]",
      "identity": {
        "type": "SystemAssigned"
      },
      "properties": {
        "publicNetworkAccess": "Enabled",
        "regionDetails": [
          {
            "location": "[parameters('location')]",
            "storageAccountDetails": [
              {
                "systemCreatedStorageAccount": {
                  "storageAccountHnsEnabled": false,
                  "storageAccountType": "Standard_LRS"
                }
              }
            ],
            "acrDetails": [
              {
                "systemCreatedAcrAccount": {
                  "acrAccountSku": "Premium"
                }
              }
            ]
          }
        ]
      }
    }
  ],
  "outputs": {
    "registryName": {
      "type": "string",
      "value": "[parameters('registryName')]"
    }
  }
}